luhn_validator/__init__.py
luhn_validator/py.typed
luhn_validator-1.2.0.post4.dist-info/LICENSE
luhn_validator-1.2.0.post4.dist-info/METADATA
luhn_validator-1.2.0.post4.dist-info/WHEEL
luhn_validator-1.2.0.post4.dist-info/top_level.txt
luhn_validator-1.2.0.post4.dist-info/RECORD
