Metadata-Version: 2.1
Name: luhn-validator
Version: 1.2.0.post4
Summary: Simple validator for identification numbers based on the Luhn algorithm
Home-page: 
Author: Mohammed Alshehri
Author-email: 
License: MIT
Keywords: luhn,validator,validation,numbers,identification,imei,credit-card
Classifier: Development Status :: 7 - Inactive
Requires-Python: >=3.7
License-File: LICENSE
